
<!-- /* main-custom-openatv -->
<!-- ********** openATV ********** -->

<!-- About -->
<screen backgroundColor="transparent" flags="wfNoBorder" name="About" position="0,0" size="1280,720" title="About">
  <widget backgroundColor="KravenBackground" font="Regular2; 26" position="70,71" render="Label" size="700,40" source="EnigmaVersion" transparent="1" />
  <widget backgroundColor="KravenBackground" font="Regular2; 26" position="70,111" render="Label" size="700,40" source="ImageVersion" transparent="1" />
  <widget backgroundColor="KravenBackground" font="Regular2; 26" position="70,151" render="Label" size="700,40" source="FPVersion" transparent="1" />
  <widget backgroundColor="KravenBackground" font="Regular2; 26" position="70,191" render="Label" size="700,40" source="TunerHeader" transparent="1" />
  <widget backgroundColor="KravenBackground" font="Regular2; 24" position="70,231" render="Label" size="700,40" source="Tuner0" transparent="1" />
  <widget backgroundColor="KravenBackground" font="Regular2; 24" position="70,271" render="Label" size="700,40" source="Tuner1" transparent="1" />
  <widget backgroundColor="KravenBackground" font="Regular2; 24" position="70,311" render="Label" size="700,40" source="Tuner2" transparent="1" />
  <widget backgroundColor="KravenBackground" font="Regular2; 24" position="70,351" render="Label" size="700,40" source="Tuner3" transparent="1" />
  <eLabel backgroundColor="KravenBackground" font="Regular2; 26" position="69,441" size="700,40" text="Support for Image: " transparent="1" />
  <eLabel backgroundColor="KravenBackground" font="Regular2; 26" position="69,480" size="700,40" text="www.opena.tv" transparent="1" />
  <widget backgroundColor="KravenBackground" font="Regular2; 26" position="70,520" render="Label" size="700,40" source="HDDHeader" transparent="1" />
  <widget backgroundColor="KravenBackground" font="Regular2; 24" position="70,560" render="Label" size="700,65" source="hddA" transparent="1" />
  <panel name="template_menu_left" />
</screen>

 <!-- AboutOE -->
<screen name="AboutOE" position="0,0" size="1280,720" title="About" flags="wfNoBorder" backgroundColor="transparent">
  <widget source="lab1" render="Label" position="70,123" size="369,35" font="Regular;30" transparent="1" zPosition="2" />
  <widget source="lab2" render="Label" position="70,173" size="370,25" font="Regular;19" transparent="1" zPosition="2" />
  <widget source="lab3" render="Label" position="70,213" size="369,25" font="Regular;19" transparent="1" zPosition="1" />
  <eLabel text="OPEN SOURCE" position="477,123" size="353,28" font="Regular2; 22" transparent="1" zPosition="1" foregroundColor="KravenFont2" />
  <eLabel text="https://github.com/openatv" position="477,173" size="352,28" font="Regular2; 19" transparent="1" zPosition="1" foregroundColor="KravenFont2" />
  <eLabel text="https://github.com/oe-alliance" position="477,213" size="354,28" font="Regular2; 19" transparent="1" zPosition="1" foregroundColor="KravenFont2" />
  <widget name="AboutScrollLabel" position="70,253" size="650,360" scrollbarMode="showOnDemand" font="Regular;20" transparent="1" zPosition="1" />
  <panel name="template_menu_left" />
</screen>

  <!-- Devices -->
<screen name="Devices" position="0,0" size="1280,720" title="SystemInfo" flags="wfNoBorder" backgroundColor="transparent">
  <widget source="TunerHeader" render="Label" position="70,121" size="458,36" font="Regular2; 20" backgroundColor="KravenBackground" transparent="1" zPosition="1" foregroundColor="KravenFont2" />
  <widget source="nims" render="Label" position="70,163" size="458,108" font="Regular;18" backgroundColor="KravenBackground" foregroundColor="KravenFont1" transparent="1" zPosition="1" enableWrapAround="0" />
  <widget source="HDDHeader" render="Label" position="70,275" size="458,36" font="Regular2; 20" transparent="1" zPosition="1" backgroundColor="KravenBackground" foregroundColor="KravenFont2" />
  <widget source="hdd" render="Label" position="70,315" size="458,112" font="Regular;18" backgroundColor="KravenBackground" foregroundColor="KravenFont1" transparent="1" zPosition="1" enableWrapAround="0" />
  <widget source="MountsHeader" render="Label" position="70,431" size="458,36" font="Regular2; 20" transparent="1" zPosition="1" backgroundColor="KravenBackground" foregroundColor="KravenFont2" />
  <widget source="mounts" render="Label" position="70,471" size="458,143" font="Regular;18" backgroundColor="KravenBackground" foregroundColor="KravenFont1" transparent="1" zPosition="1" enableWrapAround="0" />
  <widget source="global.CurrentTime" render="KravenHDEGclock" position="665,135" borderColor="KravenFont1" zPosition="4" size="80,80" transparent="1">
    <convert type="KravenHDEGAnalogic">Hours</convert>
  </widget>
  <widget source="global.CurrentTime" render="KravenHDEGclock" position="645,115" borderColor="KravenFont1" zPosition="5" size="120,120" transparent="1">
    <convert type="KravenHDEGAnalogic">Minutes</convert>
  </widget>
  <widget source="global.CurrentTime" render="KravenHDEGclock" position="645,115" borderColor="KravenFont1" zPosition="6" size="120,120" transparent="1">
    <convert type="KravenHDEGAnalogic">Seconds</convert>
  </widget>
  <ePixmap name="clock" position="630,100" size="150,150" pixmap="KravenHD/buttons/clock_bg.png" zPosition="1" alphatest="on" />
  <widget source="global.CurrentTime" render="KravenHDEGclock" position="645,315" borderColor="KravenFont2" zPosition="6" size="120,120" transparent="1">
    <convert type="AAFinfo">Harddiskspace</convert>
  </widget>
  <ePixmap name="harddiskspace" position="630,300" size="150,150" pixmap="KravenHD/buttons/gauge_bg.png" zPosition="1" alphatest="on" />
  <widget source="session.CurrentService" render="Label" position="682,397" size="50,15" font="Regular; 14" halign="center" valign="top" zPosition="7" backgroundColor="transpWhite" transparent="1" foregroundColor="KravenFont2">
    <convert type="AAFinfo">HarddiskspaceText</convert>
  </widget>
  <eLabel text="/media/hdd Used" position="609,458" size="200,25" font="Regular2; 20" halign="center" backgroundColor="KravenBackground" transparent="1" foregroundColor="KravenFont2" />
  <panel name="template_menu_left" />
</screen>

<!-- supportchannel_ListChannel_ListScreen -->
<screen name="supportchannel_ListChannel_ListScreen" position="0,0" size="1280,720" flags="wfNoBorder" backgroundColor="transparent">
  <widget name="coverArt" pixmap="~/original/images/no_coverArt.png" position="599,157" size="270,200" transparent="1" alphatest="blend" borderWidth="2" borderColor="un555556" />
  <widget name="liste" position="68,155" size="520,240" backgroundColor="KravenBackground" transparent="1" />
  <widget name="VideoPrio" position="728,369" size="105,25" backgroundColor="KravenBackground" transparent="1" foregroundColor="KravenFont1" font="Regular; 20" valign="center" halign="right" zPosition="1" />
  <widget name="vPrio" position="842,369" size="25,25" backgroundColor="KravenBackground" transparent="1" font="Regular;20" valign="center" halign="center" zPosition="1" foregroundColor="white" />
  <widget name="Page" position="684,369" size="56,25" backgroundColor="KravenBackground" transparent="1" foregroundColor="KravenFont1" font="Regular;20" valign="center" halign="right" zPosition="0" />
  <widget name="page" position="739,369" size="95,25" backgroundColor="KravenBackground" transparent="1" font="Regular;20" valign="center" halign="right" zPosition="0" />
  <eLabel backgroundColor="KravenBackground" position="0,0" size="1280,720" transparent="0" zPosition="-9" />
  <widget name="ContentTitle" position="67,110" size="800,30" backgroundColor="KravenBackground" zPosition="0" foregroundColor="white" font="Regular;22" halign="center" transparent="1" />
  <widget name="name" position="67,410" size="800,30" foregroundColor="white" backgroundColor="KravenBackground" transparent="1" font="Regular; 22" valign="top" zPosition="0" />
  <widget name="handlung" position="67,456" size="800,170" backgroundColor="KravenBackground" transparent="1" font="Regular;20" valign="top" zPosition="0" />
  <panel name="template_menu_full_button" />
  <panel name="template_colorkey_text" />
</screen>

<!-- supportchannel_YTChannel -->
<screen name="supportchannel_YTChannel" position="0,0" size="1280,720" flags="wfNoBorder" backgroundColor="transparent">
  <widget name="name" position="160,152" size="535,30" backgroundColor="KravenBackground" transparent="1" font="Regular; 22" valign="center" halign="center" />
  <widget name="ContentTitle" position="160,114" size="535,30" backgroundColor="KravenBackground" zPosition="5" foregroundColor="KravenFont2" font="Regular2; 22" halign="center" transparent="1" />
  <widget name="genreList" position="160,189" size="535,420" backgroundColor="KravenBackground" transparent="1" />
  <panel name="template_menu_left_button" />
  <panel name="template_colorkey_text" />
</screen>

<!-- InfoPanel -->
<screen name="Info" position="0,0" size="1280,720" flags="wfNoBorder" title="Panel-Info" backgroundColor="transparent">
  <widget name="label2" position="70,80" size="708,40" font="Regular;30" foregroundColor="KravenFont2" backgroundColor="KravenBackground" transparent="1" halign="center" />
  <widget name="label1" position="70,130" size="708,480" font="Regular;20" foregroundColor="KravenFont1" backgroundColor="KravenBackground" transparent="1" halign="left" />
  <panel name="template_menu_left" />
</screen>

<!-- QuickMenu -->
<screen name="QuickMenu" position="0,0" size="1280,720" backgroundColor="transparent" flags="wfNoBorder">
  <widget name="list" position="70,80" size="330,400" backgroundColor="KravenBackground" itemHeight="50" transparent="1" />
  <widget name="description" position="70,525" size="708,110" zPosition="1" font="Regular2;22" foregroundColor="KravenFont2" halign="center" backgroundColor="KravenBackground" transparent="1" />
  <widget name="sublist" position="448,80" size="330,400" backgroundColor="KravenBackground" itemHeight="50" transparent="1" />
  <panel name="template_colorkey_text" />
  <panel name="template_menu_left_button" />
</screen>

<!-- QuickMenuDevices -->
<screen name="QuickMenuDevices" position="0,0" size="1280,720" title="Devices" flags="wfNoBorder" backgroundColor="transparent">
  <widget name="lab1" position="125,148" size="618,50" font="Regular2; 20" alphatest="blend" transparent="1" halign="center" foregroundColor="KravenFont2" />
  <widget source="devicelist" render="Listbox" position="70,127" size="708,450" zPosition="3" transparent="1">
    <convert type="TemplatedMultiContent">
				{"template": [
				 MultiContentEntryText(pos = (90, 0), size = (600, 30), font=0, text = 0),
				 MultiContentEntryText(pos = (110, 30), size = (600, 50), font=1, flags = RT_VALIGN_TOP, text = 1),
				 MultiContentEntryPixmapAlphaBlend(pos = (0, 0), size = (80, 80), png = 2),
				],
				"fonts": [gFont("Regular", 24),gFont("Regular", 20)],
				"itemHeight": 85
				}
	</convert>
  </widget>
  <panel name="template_menu_left" />
</screen>

<!-- Infopanel -->
<screen backgroundColor="transparent" flags="wfNoBorder" name="Infopanel" position="0,0" size="1280,720" title="Info Panel" transparent="0">
  <widget name="Mlist" position="70,80" size="708,540" transparent="1" />
  <panel name="template_menu_left" />
</screen>

<!-- Softwarepanel -->
<screen name="SoftwarePanel" position="0,0" size="1280,720" flags="wfNoBorder" backgroundColor="transparent">
  <widget source="list" render="Listbox" position="70,90" size="708,520" backgroundColor="KravenBackground" itemHeight="50" alphatest="blend" transparent="1">
    <convert type="TemplatedMultiContent">
			{"template": [
					MultiContentEntryText(pos = (6, 2), size = (540, 28), font=0, flags = RT_HALIGN_LEFT, text = 0), # index 0 is the name
					MultiContentEntryText(pos = (6, 28), size = (540, 20), font=1, flags = RT_HALIGN_LEFT, text = 2), # index 2 is the description
					MultiContentEntryPixmapAlphaTest(pos = (605, 2), size = (48, 48), png = 4), # index 4 is the status pixmap
					MultiContentEntryPixmapAlphaTest(pos = (5, 50), size = (610, 2), png = 5), # index 4 is the div pixmap
				],
			"fonts": [gFont("Regular", 22),gFont("Regular", 14)],
			"itemHeight": 52
			}
	</convert>
  </widget>
  <widget name="packagetext" position="918,391" size="250,30" zPosition="1" font="Regular2; 25" halign="right" transparent="1" backgroundColor="KravenBackground" foregroundColor="KravenFont2" />
  <widget name="packagenr" position="1181,391" size="50,30" zPosition="1" font="Regular2; 25" halign="right" transparent="1" backgroundColor="KravenBackground" foregroundColor="KravenFont2" />
  <widget name="feedstatusRED" position="997,557" size="200,30" zPosition="1" font="Regular;25" halign="left" backgroundColor="KravenBackground" foregroundColor="KravenFont1" transparent="1" />
  <widget name="feedstatusYELLOW" position="997,587" size="200,30" zPosition="1" font="Regular;25" halign="left" backgroundColor="KravenBackground" foregroundColor="KravenFont1" transparent="1" />
  <widget name="feedstatusGREEN" position="997,617" size="200,30" zPosition="1" font="Regular;25" halign="left" backgroundColor="KravenBackground" foregroundColor="KravenFont1" transparent="1" />
  <widget name="a_off" pixmap="/usr/lib/enigma2/python/Plugins/Extensions/Infopanel/icons/aoff.png" position="954,551" zPosition="1" size="36,97" alphatest="on" />
  <widget name="a_red" pixmap="/usr/lib/enigma2/python/Plugins/Extensions/Infopanel/icons/ared.png" position="954,551" zPosition="1" size="36,97" alphatest="on" />
  <widget name="a_yellow" pixmap="/usr/lib/enigma2/python/Plugins/Extensions/Infopanel/icons/ayellow.png" position="954,551" zPosition="1" size="36,97" alphatest="on" />
  <widget name="a_green" pixmap="/usr/lib/enigma2/python/Plugins/Extensions/Infopanel/icons/agreen.png" position="954,551" zPosition="1" size="36,97" alphatest="on" />
  <panel name="template_colorkey_text" />
  <panel name="template_menu_full_button" />
</screen>

<!-- SoftcamPanel -->
<screen name="SoftcamPanel" position="0,0" size="1280,720" title="Softcam Panel" backgroundColor="transparent" flags="wfNoBorder">
  <widget name="config" font="Regular; 20" position="70,126" size="500,100" enableWrapAround="1" foregroundColor="KravenFont1" backgroundColor="KravenBackground" transparent="1" />
  <widget font="Regular2; 22" name="enigma2" position="591,164" size="185,25" transparent="1" backgroundColor="KravenBackground" foregroundColor="KravenFont2" />
  <widget font="Regular2; 20" name="actifcam" position="70,235" size="352,64" transparent="1" backgroundColor="KravenBackground" foregroundColor="KravenFont2" />
  <widget font="Regular2; 20" name="actifcam2" position="426,235" size="352,64" transparent="1" backgroundColor="KravenBackground" foregroundColor="KravenFont2" />
  <widget font="Regular; 20" name="ecminfo" position="70,308" size="708,300" foregroundColor="KravenFont1" backgroundColor="KravenBackground" transparent="1" />
  <panel name="template_colorkey_text" />
  <panel name="template_menu_left_button" />
</screen>

<!-- ShowSoftcamPanelExtensions -->
<screen name="ShowSoftcamPanelExtensions" position="0,0" size="1280,720" title="Softcam-Panel Setup" flags="wfNoBorder" backgroundColor="transparent">
  <widget name="config" position="70,80" size="708,540" enableWrapAround="1" backgroundColor="KravenBackground" transparent="1" />
  <panel name="template_colorkey_text" />
  <panel name="template_menu_left_button" />
</screen>

<!-- ShowSoftcamPackages -->
<screen name="ShowSoftcamPackages" position="0,0" size="1280,720" title="New Packages" flags="wfNoBorder" backgroundColor="transparent">
  <widget source="list" render="Listbox" position="70,80" size="708,540" transparent="1" foregroundColorSelected="white">
    <convert type="TemplatedMultiContent">
				{"template": [
						MultiContentEntryPixmapAlphaTest(pos = (18, 5), size = (48, 48), png = 4), # index 4 is the status pixmap
						MultiContentEntryText(pos = (90, 5), size = (650, 28), font=0, flags = RT_HALIGN_LEFT, text = 0), # index 0 is the name
						MultiContentEntryText(pos = (100, 35), size = (650, 20), font=1, flags = RT_HALIGN_LEFT, text = 2, color=0x8A8787, color_sel=0x8A8787), # index 2 is the description
						MultiContentEntryPixmapAlphaTest(pos = (5, 58), size = (0, 0), png = 5), # index 4 is the div pixmap
					],
				"fonts": [gFont("Regular", 22),gFont("Regular", 16)],
				"itemHeight": 60
				}
	</convert>
  </widget>
  <panel name="template_colorkey_text" />
  <panel name="template_menu_left_button" />
</screen>


<!-- DevicePanelConf -->
<screen name="DevicePanelConf" position="0,0" size="1280,720" title="DevicePanelConf" backgroundColor="transparent" flags="wfNoBorder">
  <widget name="config" position="70,120" size="700,371" enableWrapAround="1" backgroundColor="KravenBackground" transparent="1" />
  <widget name="Linconn" position="70,505" size="700,20" font="Regular2; 18" halign="center" valign="center" foregroundColor="KravenFont2" />
  <panel name="template_colorkey_text" />
  <panel name="template_menu_left_button" />
</screen>

<!-- HddMount -->
<screen name="HddMount" position="0,0" size="1280,720" title="HddMount" flags="wfNoBorder" backgroundColor="transparent">
  <widget source="list" render="Listbox" position="70,120" size="700,371" font="Regular;16" transparent="1">
    <convert type="TemplatedMultiContent">
				{"template": [
				 MultiContentEntryText(pos = (90, 0), size = (600, 30), font=0, text = 0),
				 MultiContentEntryText(pos = (110, 30), size = (600, 50), font=1, flags = RT_VALIGN_TOP, text = 1),
				 MultiContentEntryPixmapAlphaBlend(pos = (0, 0), size = (80, 80), png = 2),
				],
				"fonts": [gFont("Regular", 24),gFont("Regular", 20)],
				"itemHeight": 85
				}
	</convert>
  </widget>
  <widget backgroundColor="KravenBackground" name="lab1" zPosition="2" position="126,129" size="600,40" font="Regular2; 22" halign="center" transparent="1" foregroundColor="KravenFont2" />
  <panel name="template_colorkey_text" />
  <panel name="template_menu_left_button" />
</screen>

<!-- HarddiskSelection -->
<screen backgroundColor="transparent" flags="wfNoBorder" name="HarddiskSelection" position="0,0" size="1280,720" title="Select HDD">
  <widget itemHeight="30" name="hddlist" position="70,80" size="708,540" transparent="1" />
  <panel name="template_menu_left" />
</screen>

<!-- HarddiskSetup -->
<screen backgroundColor="transparent" flags="wfNoBorder" name="HarddiskSetup" position="0,0" size="1280,720" title="Harddisk">
  <widget font="Regular2;23" name="model" position="70,150" size="700,25" transparent="1" />
  <widget font="Regular2;23" name="capacity" position="70,200" size="700,25" transparent="1" />
  <widget font="Regular2;23" name="bus" position="70,250" size="700,25" transparent="1" />
  <widget backgroundColor="KravenBackground" font="Regular2;20" name="initializetext" position="18,618" size="816,24" transparent="1" zPosition="1" foregroundColor="KravenFont2" />
  <panel name="template_colorkey_text" />
  <panel name="template_menu_left_button" />
</screen>

<!-- HarddiskWait -->
<screen backgroundColor="transparent" flags="wfNoBorder" name="HarddiskWait" position="0,0" size="1280,720">
  <widget name="wait" position="70,80" size="708,540" transparent="1" />
  <panel name="template_menu_left" />
</screen>

<!-- DriverManagerFile -->
<screen flags="wfNoBorder" name="DriverManagerFile" position="0,0" size="1280,720" title="Select file to execute" transparent="0" backgroundColor="transparent">
  <widget backgroundColor="KravenBackground" font="Regular2;23" name="driverfile" position="70,74" size="708,28" transparent="1" foregroundColor="KravenFont2" />
  <widget backgroundColor="KravenBackground" itemHeight="30" name="filelist" position="70,107" size="708,540" transparent="1" zPosition="3" />
  <panel name="template_colorkey_text_source" />
  <panel name="template_menu_left_button" />
</screen>
  
<!-- ButtonSetup -->
<screen backgroundColor="transparent" flags="wfNoBorder" name="HotkeySetup" position="0,0" size="1280,720" title="Tasteneinstellungen">
  <widget name="list" position="40,99" size="385,529" scrollbarMode="showOnDemand" font="Regular;22" itemHeight="28" transparent="1" foregroundColor="white" enableWrapAround="1" backgroundColor="KravenBackground" zPosition="-8" />
  <widget name="choosen" position="427,99" size="385,530" scrollbarMode="showOnDemand" font="Regular2; 22" itemHeight="28" foregroundColor="KravenFont1" backgroundColor="KravenBackground" zPosition="-8" />
  <widget name="description" position="934,255" size="302,250" font="Regular2; 16" foregroundColor="KravenFont2" valign="center" halign="center" backgroundColor="KravenBackground" zPosition="-8" />
  <panel name="template_colorkey_text_source" />
  <panel name="template_menu_full_button" />
</screen>

<!-- ButtonSetupSelect -->
<screen backgroundColor="transparent" flags="wfNoBorder" name="ButtonSetupSelect" position="0,0" size="1280,720" title="Tasteneinstellungen">
  <widget name="list" position="40,99" size="385,529" scrollbarMode="showOnDemand" font="Regular;22" itemHeight="28" transparent="1" foregroundColor="white" enableWrapAround="1" backgroundColor="KravenBackground" zPosition="-8" />
  <widget name="choosen" position="427,99" size="385,530" scrollbarMode="showOnDemand" font="Regular2; 22" itemHeight="28" foregroundColor="KravenFont1" backgroundColor="KravenBackground" zPosition="-8" />
  <widget name="description" position="934,255" size="302,250" font="Regular2; 16" foregroundColor="KravenFont2" valign="center" halign="center" backgroundColor="KravenBackground" zPosition="-8" />
  <panel name="template_colorkey_text_source" />
  <panel name="template_menu_full_button" />
</screen>

<!-- Animation -->
<screen backgroundColor="transparent" flags="wfNoBorder" name="AnimationSetupScreen" position="0,0" size="1280,720" title="Animation Setup">
  <widget backgroundColor="KravenBackground" name="list" itemHeight="30" font="Regular;22" foregroundColor="KravenFont1" position="70,80" size="708,510" scrollbarMode="showOnDemand" transparent="1" />
  <panel name="template_menu_left_button" />
  <panel name="template_colorkey_text_source" />
</screen>

<!-- AnimationSetupConfig -->
<screen backgroundColor="transparent" flags="wfNoBorder" name="AnimationSetupConfig" position="0,0" size="1280,720" title="AnimationSetupConfig">
  <widget backgroundColor="KravenBackground" name="config" itemHeight="30" font="Regular;22" foregroundColor="KravenFont1" position="70,80" size="708,100" scrollbarMode="showOnDemand" transparent="1" />
  <panel name="template_menu_left_button" />
  <panel name="template_colorkey_text_source" />
</screen>

<!-- Tastenbelegung -->
<screen backgroundColor="transparent" flags="wfNoBorder" name="ButtonSetup" position="0,0" size="1280,720" title="">
  <widget backgroundColor="KravenBackground" name="list" itemHeight="30" font="Regular;22" foregroundColor="KravenFont1" position="70,80" size="708,420" scrollbarMode="showOnDemand" transparent="1" />
  <widget backgroundColor="KravenBackground" name="description" position="70,548" size="708,67" zPosition="2" font="Regular2;22" foregroundColor="KravenFont2" valign="center" halign="center" transparent="1" />
  <panel name="template_menu_left" />
</screen>
<!-- main-custom-openatv */ -->
